Metadata-Version: 1.0
Name: bin-parcer
Version: 1.3
Summary: a utility lib for parsing text bins
Home-page: https://github.com/hiikion/pastebinOmatic
Author: hiikion
Author-email: UNKNOWN
License: MPL-2.0 License
Platform: UNKNOWN
